[
    {
        "id": 17960201365066315,
        "created_at": 1532766119,
        "text": "\ud83d\ude3b\ud83d\ude3b\ud83d\ude3b\ud83d\ude3b\ud83d\ude3b\ud83d\ude3b",
        "owner": {
            "id": "259392777",
            "is_verified": false,
            "profile_pic_url": "https://scontent-arn2-2.cdninstagram.com/v/t51.2885-19/s150x150/53283801_818234695207500_2841413594095026176_n.jpg?_nc_ht=scontent-arn2-2.cdninstagram.com&_nc_cat=100&_nc_ohc=4qh3JWEM6KgAX_G3j1r&edm=AMrZAGUBAAAA&ccb=7-4&oh=00_AT_pdSFpNtqkRIRljaPknl5kSu-PjK95rNy1E_LBdmQDxA&oe=61D3D3F3&_nc_sid=9fb510",
            "username": "pavlenkodaria"
        },
        "likes_count": 0,
        "answers": []
    },
    {
        "id": 17951439598106115,
        "created_at": 1532728104,
        "text": "\u043b\u0443\u043d\u043d\u0430\u044f \u043f\u0440\u0438\u0437\u043c\u0430, \u0434\u0430\u0439 \u043c\u043d\u0435 \u0441\u0438\u043b!",
        "owner": {
            "id": "378722265",
            "is_verified": false,
            "profile_pic_url": "https://scontent-arn2-1.cdninstagram.com/v/t51.2885-19/s150x150/23498229_500742806949591_1660423172538761216_n.jpg?_nc_ht=scontent-arn2-1.cdninstagram.com&_nc_cat=103&_nc_ohc=LYfxOvnpqdEAX_Zz8Nb&edm=AMrZAGUBAAAA&ccb=7-4&oh=00_AT99EiK183GT-VS6vT0f8a31gV3vLbEYbwpmg9ztx78_8w&oe=61D32ED6&_nc_sid=9fb510",
            "username": "alinamoteva"
        },
        "likes_count": 0,
        "answers": []
    }
]